MANIFEST.in
setup.py
gxddk/__init__.py
gxddk/conf.py
gxddk/gxddkbuild.py
gxddk/index.rst
gxddk.egg-info/PKG-INFO
gxddk.egg-info/SOURCES.txt
gxddk.egg-info/dependency_links.txt
gxddk.egg-info/entry_points.txt
gxddk.egg-info/top_level.txt
gxddk/scripts/envexec
gxddk/scripts/_ext/genmodule.py
gxddk/scripts/_ext/retex.py
gxddk/scripts/_ext/rst_table.py
gxddk/scripts/_static/style.css
gxddk/scripts/_templates/layout.html
gxddk/scripts/_templates/search.html