Metadata-Version: 1.0
Name: gxddk
Version: 1.2.6
Summary: sphinx doc build
Home-page: UNKNOWN
Author: zhaobk
Author-email: zhaobk@nationalchip.com
License: UNKNOWN
Keywords: sphinx doc
Platform: UNKNOWN
